notazz
